ssebowa/__init__.py
ssebowa/__version__.py
ssebowa/hello.py
ssebowa/img_finetune.py
ssebowa/ssebowa_imgen.py
ssebowa/ssebowa_vllm.py
ssebowa/scripts/__init__.py
ssebowa/scripts/infer/__init__.py
ssebowa/scripts/infer/sd_dreambooth/__init__.py
ssebowa/scripts/infer/sd_dreambooth/inference.py
ssebowa/scripts/infer/sd_dreambooth/requirements.txt
ssebowa/scripts/infer/sd_dreambooth_lora/__init__.py
ssebowa/scripts/infer/sd_dreambooth_lora/inference.py
ssebowa/scripts/infer/sd_dreambooth_lora/requirements.txt
ssebowa/scripts/infer/sdxl_dreambooth_lora/__init__.py
ssebowa/scripts/infer/sdxl_dreambooth_lora/inference.py
ssebowa/scripts/infer/sdxl_dreambooth_lora/requirements.txt
ssebowa/scripts/infer/sdxl_dreambooth_lora_advanced/__init__.py
ssebowa/scripts/infer/sdxl_dreambooth_lora_advanced/inference.py
ssebowa/scripts/infer/sdxl_dreambooth_lora_advanced/requirements.txt
ssebowa/scripts/train/__init__.py
ssebowa/scripts/train/requirements.txt
ssebowa/scripts/train/train_sd_dreambooth.py
ssebowa/scripts/train/train_sd_dreambooth_lora.py
ssebowa/scripts/train/train_sdxl_dreambooth_lora.py
ssebowa/scripts/train/train_sdxl_dreambooth_lora_advanced.py
ssebowa/utils/__init__.py
ssebowa/utils/aws_helpers.py
ssebowa/utils/image_helpers.py
ssebowa/utils/misc.py
ssebowa/utils/prompt_helpers.py
ssebowa-2.8.dist-info/LICENSE
ssebowa-2.8.dist-info/METADATA
ssebowa-2.8.dist-info/WHEEL
ssebowa-2.8.dist-info/top_level.txt
ssebowa-2.8.dist-info/RECORD
