Metadata-Version: 2.1
Name: ssebowa
Version: 2.8
Summary: Ssebowa is an open source Python library that provides generative AI models!
Home-page: https://github.com/SsebowaDisan/ssebowa
Author: Ssebowa Disan
Author-email: info@ssebowa.com
License: MIT
Classifier: Development Status :: 3 - Alpha
Classifier: Intended Audience :: Developers
Classifier: Natural Language :: English
Classifier: Programming Language :: Python
Classifier: Programming Language :: Python :: 3
Classifier: Programming Language :: Python :: 3.7
Classifier: Programming Language :: Python :: 3.8
Classifier: Programming Language :: Python :: 3.9
Classifier: Programming Language :: Python :: 3.10
Requires-Python: >=3.7.0
License-File: LICENSE
Requires-Dist: accelerate (>=0.25.0)
Requires-Dist: autocrop (>=1.3.0)
Requires-Dist: awscli (>=1.31.12)
Requires-Dist: bitsandbytes (>=0.41.0)
Requires-Dist: deepspeed (>=0.12.6)
Requires-Dist: diffusers (==0.25.0)
Requires-Dist: matplotlib (>=3.8.0)
Requires-Dist: peft (==0.7.1)
Requires-Dist: pillow (>=10.0.1)
Requires-Dist: prodigyopt (>=1.0)
Requires-Dist: safetensors (>=0.4.1)
Requires-Dist: sagemaker (>=2.199.0)
Requires-Dist: tensorboard (>=2.15.1)
Requires-Dist: torch (==2.0.1)
Requires-Dist: torchvision (>=0.15.2)
Requires-Dist: tqdm (>=4.66.1)
Requires-Dist: transformers (==4.36.2)
Requires-Dist: wandb (>=0.16.1)
Requires-Dist: xformers (>=0.0.19)
Requires-Dist: py-dreambooth
Provides-Extra: test
Requires-Dist: black ; extra == 'test'
Requires-Dist: coverage ; extra == 'test'
Requires-Dist: flake8 ; extra == 'test'
Requires-Dist: mock ; extra == 'test'
Requires-Dist: pydocstyle ; extra == 'test'
Requires-Dist: pytest ; extra == 'test'
Requires-Dist: pytest-cov ; extra == 'test'
Requires-Dist: tox ; extra == 'test'
